stackit/logme/__init__.py
stackit/logme/api/__init__.py
stackit/logme/api/default_api.py
stackit/logme/api_client.py
stackit/logme/api_response.py
stackit/logme/configuration.py
stackit/logme/exceptions.py
stackit/logme/models/__init__.py
stackit/logme/models/backup.py
stackit/logme/models/create_backup_response_item.py
stackit/logme/models/create_instance_payload.py
stackit/logme/models/create_instance_response.py
stackit/logme/models/credentials.py
stackit/logme/models/credentials_list_item.py
stackit/logme/models/credentials_response.py
stackit/logme/models/error.py
stackit/logme/models/get_metrics_response.py
stackit/logme/models/instance.py
stackit/logme/models/instance_last_operation.py
stackit/logme/models/instance_parameters.py
stackit/logme/models/instance_parameters_groks_inner.py
stackit/logme/models/instance_schema.py
stackit/logme/models/list_backups_response.py
stackit/logme/models/list_credentials_response.py
stackit/logme/models/list_instances_response.py
stackit/logme/models/list_offerings_response.py
stackit/logme/models/list_restores_response.py
stackit/logme/models/model_schema.py
stackit/logme/models/offering.py
stackit/logme/models/partial_update_instance_payload.py
stackit/logme/models/plan.py
stackit/logme/models/raw_credentials.py
stackit/logme/models/restore.py
stackit/logme/models/trigger_restore_response.py
stackit/logme/models/update_backups_config_payload.py
stackit/logme/models/update_backups_config_response.py
stackit/logme/py.typed
stackit/logme/rest.py
stackit_logme-0.4.0.dist-info/LICENSE.md
stackit_logme-0.4.0.dist-info/METADATA
stackit_logme-0.4.0.dist-info/NOTICE.txt
stackit_logme-0.4.0.dist-info/WHEEL
stackit_logme-0.4.0.dist-info/RECORD
